[
  {
    "keyword": "mireva fit™ thigh & pelvic trainer",
    "search_volume_exact": 276,
    "ppc_bid_exact": null,
    "relevancy_score": 533
  },
  {
    "keyword": "kegel exercises",
    "search_volume_exact": 279,
    "ppc_bid_exact": null,
    "relevancy_score": 533
  },
  {
    "keyword": "pelvic massagers woman",
    "search_volume_exact": 280,
    "ppc_bid_exact": null,
    "relevancy_score": 256
  },
  {
    "keyword": "kegel trainer, pelvic health for men",
    "search_volume_exact": 287,
    "ppc_bid_exact": null,
    "relevancy_score": 741
  },
  {
    "keyword": "kegel balls exercise with vibration",
    "search_volume_exact": 290,
    "ppc_bid_exact": null,
    "relevancy_score": 306
  },
  {
    "keyword": "kgoal boost kegel exerciser for men",
    "search_volume_exact": 297,
    "ppc_bid_exact": null,
    "relevancy_score": 386
  },
  {
    "keyword": "pelvistep",
    "search_volume_exact": 297,
    "ppc_bid_exact": null,
    "relevancy_score": 323
  },
  {
    "keyword": "adductor",
    "search_volume_exact": 298,
    "ppc_bid_exact": null,
    "relevancy_score": 89
  },
  {
    "keyword": "workout tools for women",
    "search_volume_exact": 299,
    "ppc_bid_exact": null,
    "relevancy_score": 107
  },
  {
    "keyword": "easy exercise equipment for women",
    "search_volume_exact": 307,
    "ppc_bid_exact": null,
    "relevancy_score": 87
  }
]