[
  {
    "asin": "B0FDJB1TRP",
    "brand": "HotokGoo",
    "revenue": 1528.98,
    "reviews": 68
  },
  {
    "asin": "B0G25L7XYH",
    "brand": "TWGRNF",
    "revenue": 2069.31,
    "reviews": 126
  },
  {
    "asin": "B0FM3V43YB",
    "brand": "Kibuhain",
    "revenue": 1637.37,
    "reviews": 94
  },
  {
    "asin": "B0FN7ZYZF6",
    "brand": "HGJSYUTM",
    "revenue": 21714.57,
    "reviews": 94
  },
  {
    "asin": "B0DCBN12RP",
    "brand": "ZEMBSOYA",
    "revenue": 1238.79,
    "reviews": 28
  },
  {
    "asin": "B0FJXYWRFH",
    "brand": "GIOIGOO",
    "revenue": 201629.58,
    "reviews": 32
  },
  {
    "asin": "B0FK573TYN",
    "brand": "GIOIGOO",
    "revenue": 1519.62,
    "reviews": 66
  },
  {
    "asin": "B0CM6LPG7M",
    "brand": "MIWEN",
    "revenue": 10555.2,
    "reviews": 110
  },
  {
    "asin": "B0FNR514ZJ",
    "brand": "AERX",
    "revenue": 1847.34,
    "reviews": 70
  },
  {
    "asin": "B0DK94VHCN",
    "brand": "ES Tech",
    "revenue": 1759.56,
    "reviews": 1
  },
  {
    "asin": "B0FP4C1VKR",
    "brand": "ABXMAS",
    "revenue": 2249.75,
    "reviews": 383
  },
  {
    "asin": "B0FWC5DD65",
    "brand": "AGPTEK",
    "revenue": 2127.72,
    "reviews": 93
  },
  {
    "asin": "B09B3XVFTT",
    "brand": "AKASO",
    "revenue": 1439.82,
    "reviews": 225
  },
  {
    "asin": "B0FF4NRRRC",
    "brand": "ALLJOY",
    "revenue": 9572.58,
    "reviews": 96
  },
  {
    "asin": "B0FH1SJLD2",
    "brand": "AOBOCO",
    "revenue": 14898.51,
    "reviews": 119
  },
  {
    "asin": "B0FZ9ZW65G",
    "brand": "AOKESTE",
    "revenue": 63293.67,
    "reviews": 135
  },
  {
    "asin": "B0DCV9V5VQ",
    "brand": "AOKESTE",
    "revenue": 3599.4,
    "reviews": 175
  },
  {
    "asin": "B0FFN1BGMV",
    "brand": "ARRIS",
    "revenue": 10427.02,
    "reviews": 21
  },
  {
    "asin": "B0FZJNJS5R",
    "brand": "Acroutro",
    "revenue": 11947.61,
    "reviews": 180
  }
]